{
  "GlobalConfiguration": {
    "BaseUrl": "http://localhost:5229"
  },
  "Routes": [
    {
      "UpstreamPathTemplate": "/gateway/drivers/{everything}",
      "UpstreamHttpMethod": [ "Get", "Post", "Put" ],
      "DownstreamPathTemplate": "/api/drivers/{everything}",
      "DownstreamScheme": "http",
      "DownstreamHostAndPorts": [
        {
          "Host": "localhost",
          "Port": 5208
        }
      ]
    },
    {
      "UpstreamPathTemplate": "/gateway/achievement/{everything}",
      "UpstreamHttpMethod": [ "Get", "Post", "Put" ],
      "DownstreamPathTemplate": "/api/achievement/{everything}",
      "DownstreamScheme": "http",
      "DownstreamHostAndPorts": [
        {
          "Host": "localhost",
          "Port": 5044
        }
      ]
    },
    {
      "UpstreamPathTemplate": "/gateway/driverstats/{everything}",
      "UpstreamHttpMethod": [ "Get" ],
      "DownstreamPathTemplate": "/api/driverstats/{everything}",
      "DownstreamScheme": "http",
      "DownstreamHostAndPorts": [
        {
          "Host": "localhost",
          "Port": 5221
        }
      ]
    }
  ]
}
